{
  "label": "이번주 (2026-05-11 ~ 2026-05-17)",
  "start_date": "2026-05-11",
  "end_date": "2026-05-17",
  "ads_analyzed": 506,
  "method": "ai_refined",
  "generated_at": "2026-05-17T12:05:52.644376+09:00",
  "top20": [
    {
      "expression": "리프팅",
      "count": 25,
      "examples": [
        "260511-중-212566",
        "260511-중-212567",
        "260511-중-212575"
      ]
    },
    {
      "expression": "재활치료",
      "count": 18,
      "examples": [
        "260511-중-212560",
        "260512-중-212746",
        "260512-중-212747"
      ]
    },
    {
      "expression": "정형외과",
      "count": 17,
      "examples": [
        "260511-중-212560",
        "260511-중-212674",
        "260512-중-212690"
      ]
    },
    {
      "expression": "비수술치료",
      "count": 16,
      "examples": [
        "260511-중-212577",
        "260511-중-212579",
        "260511-중-212592"
      ]
    },
    {
      "expression": "내시경",
      "count": 15,
      "examples": [
        "260511-중-212605",
        "260511-중-212606",
        "260511-중-212607"
      ]
    },
    {
      "expression": "건강검진",
      "count": 12,
      "examples": [
        "260511-중-212558",
        "260511-중-212605",
        "260511-중-212606"
      ]
    },
    {
      "expression": "야간진료",
      "count": 12,
      "examples": [
        "260511-중-212577",
        "260511-중-212623",
        "260511-중-212625"
      ]
    },
    {
      "expression": "주름개선",
      "count": 11,
      "examples": [
        "260511-중-212564",
        "260511-중-212615",
        "260511-중-212616"
      ]
    },
    {
      "expression": "레이저제모",
      "count": 11,
      "examples": [
        "260511-중-212567",
        "260512-중-212743",
        "260512-중-212761"
      ]
    },
    {
      "expression": "도수치료",
      "count": 9,
      "examples": [
        "260511-중-212560",
        "260512-중-212691",
        "260512-중-212692"
      ]
    },
    {
      "expression": "백내장수술",
      "count": 10,
      "examples": [
        "260511-중-212597",
        "260511-중-212598",
        "260511-중-212642"
      ]
    },
    {
      "expression": "내시경수술",
      "count": 9,
      "examples": [
        "260512-중-212748",
        "260512-중-212749",
        "260512-중-212750"
      ]
    },
    {
      "expression": "개별맞춤치료",
      "count": 7,
      "examples": [
        "260512-중-212746",
        "260512-중-212757",
        "260512-중-212762"
      ]
    },
    {
      "expression": "안면거상",
      "count": 7,
      "examples": [
        "260512-중-212698",
        "260512-중-212715",
        "260512-중-212716"
      ]
    },
    {
      "expression": "가슴성형",
      "count": 7,
      "examples": [
        "260512-중-212738",
        "260513-중-212823",
        "260513-중-212848"
      ]
    },
    {
      "expression": "미니리프팅",
      "count": 7,
      "examples": [
        "260514-중-212936",
        "260514-중-212937",
        "260514-중-212938"
      ]
    },
    {
      "expression": "빠른회복",
      "count": 6,
      "examples": [
        "260511-중-212584",
        "260511-중-212634",
        "260512-중-212746"
      ]
    },
    {
      "expression": "체외충격파",
      "count": 6,
      "examples": [
        "260512-중-212690",
        "260512-중-212691",
        "260512-중-212692"
      ]
    },
    {
      "expression": "전문의",
      "count": 22,
      "examples": [
        "260511-중-212593",
        "260511-중-212674",
        "260512-중-212690"
      ]
    },
    {
      "expression": "진료시간",
      "count": 20,
      "examples": [
        "260511-중-212575",
        "260511-중-212578",
        "260511-중-212647"
      ]
    }
  ]
}